super_scad_hole/Hole.py
super_scad_hole/HoleAlignment.py
super_scad_hole/HoleCounterbored.py
super_scad_hole/HoleCounterboredSlotted.py
super_scad_hole/HoleCounterdrilled.py
super_scad_hole/HoleCounterdrilledSlotted.py
super_scad_hole/HoleCountersunk.py
super_scad_hole/HoleCountersunkSlotted.py
super_scad_hole/HoleRotationMixin.py
super_scad_hole/HoleRotationSlottedMixin.py
super_scad_hole/HoleSimple.py
super_scad_hole/HoleSimpleSlotted.py
super_scad_hole/__init__.py
super_scad_hole-0.9.1.dist-info/LICENSE
super_scad_hole-0.9.1.dist-info/METADATA
super_scad_hole-0.9.1.dist-info/WHEEL
super_scad_hole-0.9.1.dist-info/RECORD
